MANIFEST.in
README.md
setup.py
OASYS1_XRayServer.egg-info/PKG-INFO
OASYS1_XRayServer.egg-info/SOURCES.txt
OASYS1_XRayServer.egg-info/dependency_links.txt
OASYS1_XRayServer.egg-info/entry_points.txt
OASYS1_XRayServer.egg-info/namespace_packages.txt
OASYS1_XRayServer.egg-info/not-zip-safe
OASYS1_XRayServer.egg-info/requires.txt
OASYS1_XRayServer.egg-info/top_level.txt
orangecontrib/__init__.py
orangecontrib/xrayserver/__init__.py
orangecontrib/xrayserver/util/__init__.py
orangecontrib/xrayserver/util/xrayserver_util.py
orangecontrib/xrayserver/widgets/__init__.py
orangecontrib/xrayserver/widgets/gui/__init__.py
orangecontrib/xrayserver/widgets/gui/ow_xrayserver_widget.py
orangecontrib/xrayserver/widgets/xrayserver/__init__.py
orangecontrib/xrayserver/widgets/xrayserver/list_utility.py
orangecontrib/xrayserver/widgets/xrayserver/ow_gid_sl.py
orangecontrib/xrayserver/widgets/xrayserver/ow_ter_sl.py
orangecontrib/xrayserver/widgets/xrayserver/ow_x0h.py
orangecontrib/xrayserver/widgets/xrayserver/ow_x0p.py
orangecontrib/xrayserver/widgets/xrayserver/icons/gidsl.png
orangecontrib/xrayserver/widgets/xrayserver/icons/list.png
orangecontrib/xrayserver/widgets/xrayserver/icons/no_standing_waves_result.png
orangecontrib/xrayserver/widgets/xrayserver/icons/tersl.png
orangecontrib/xrayserver/widgets/xrayserver/icons/x0h.png
orangecontrib/xrayserver/widgets/xrayserver/icons/x0p.png
orangecontrib/xrayserver/widgets/xrayserver/icons/xrayserver.png