Metadata-Version: 2.1
Name: OASYS1-XRayServer
Version: 1.0.37
Summary: X-Ray Server: Sergey Stepanov's X-Ray Server on OASYS
Home-page: https://github.com/oasys-kit/XRayServer
Download-URL: https://github.com/oasys-kit/XRayServer
Author: Luca Rebuffi
Author-email: lrebuffi@anl.gov
License: GPLv3
Keywords: X-ray optics,simulator,oasys1
Classifier: Development Status :: 5 - Production/Stable
Classifier: Environment :: X11 Applications :: Qt
Classifier: Environment :: Console
Classifier: Environment :: Plugins
Classifier: Programming Language :: Python :: 3
Classifier: Intended Audience :: Science/Research
Requires-Dist: oasys1>=1.2.108
Requires-Dist: PyQtWebEngine==5.14
